cdo_local_uuid/__init__.py
cdo_local_uuid/py.typed
cdo_local_uuid-0.5.0.dist-info/LICENSE
cdo_local_uuid-0.5.0.dist-info/METADATA
cdo_local_uuid-0.5.0.dist-info/THIRD_PARTY_LICENSES.md
cdo_local_uuid-0.5.0.dist-info/WHEEL
cdo_local_uuid-0.5.0.dist-info/top_level.txt
cdo_local_uuid-0.5.0.dist-info/RECORD
